htithermal/__init__.py
htithermal/src/__init__.py
htithermal/src/_version.py
htithermal/src/htithermal.py
htithermal/src/utils.py
htithermal/test/__init__.py
htithermal/test/test_htithermal.py
htithermal-0.0.1.dist-info/LICENSE
htithermal-0.0.1.dist-info/METADATA
htithermal-0.0.1.dist-info/WHEEL
htithermal-0.0.1.dist-info/top_level.txt
htithermal-0.0.1.dist-info/RECORD
