Metadata-Version: 2.1
Name: htithermal
Version: 0.0.1
Summary: A package to plot AI/ML metrics at ease
Home-page: https://github.com/somexgupta/htithermal
Author: SomexGupta
Author-email: gupta.somex@gmail.com
License: MIT
Classifier: License :: OSI Approved :: MIT License
Classifier: Programming Language :: Python :: 3.8
Classifier: Operating System :: OS Independent
Requires-Python: >=3.7
License-File: LICENSE
Requires-Dist: pillow (>=7.0.0)
Requires-Dist: numpy (>=1.19.2)
Provides-Extra: dev
Requires-Dist: pytest (>=7.0) ; extra == 'dev'
Requires-Dist: twine (>=4.0.2) ; extra == 'dev'
